olah/__init__.py
olah/configs.py
olah/constants.py
olah/errors.py
olah/server.py
olah/auth/__init__.py
olah/cache/__init__.py
olah/cache/bitset.py
olah/cache/olah_cache.py
olah/cache/stat.py
olah/database/__init__.py
olah/database/models.py
olah/mirror/__init__.py
olah/mirror/meta.py
olah/mirror/repos.py
olah/proxy/__init__.py
olah/proxy/commits.py
olah/proxy/files.py
olah/proxy/lfs.py
olah/proxy/meta.py
olah/proxy/pathsinfo.py
olah/proxy/tree.py
olah/static/index.html
olah/static/repos.html
olah/utils/__init__.py
olah/utils/cache_utils.py
olah/utils/disk_utils.py
olah/utils/file_utils.py
olah/utils/logging.py
olah/utils/olah_utils.py
olah/utils/repo_utils.py
olah/utils/rule_utils.py
olah/utils/url_utils.py
olah/utils/zip_utils.py
olah-0.4.1.dist-info/LICENSE
olah-0.4.1.dist-info/METADATA
olah-0.4.1.dist-info/WHEEL
olah-0.4.1.dist-info/entry_points.txt
olah-0.4.1.dist-info/top_level.txt
olah-0.4.1.dist-info/RECORD
