Metadata-Version: 2.2
Name: olah
Version: 0.4.1
Summary: Self-hosted lightweight huggingface mirror.
Project-URL: Homepage, https://github.com/vtuber-plan/olah
Project-URL: Bug Tracker, https://github.com/vtuber-plan/olah/issues
Classifier: Programming Language :: Python :: 3
Classifier: License :: OSI Approved :: MIT License
Requires-Python: >=3.8
License-File: LICENSE
Requires-Dist: fastapi
Requires-Dist: fastapi-utils
Requires-Dist: httpx
Requires-Dist: numpy
Requires-Dist: pydantic<=2.8.2
Requires-Dist: pydantic-settings<=2.4.0
Requires-Dist: requests
Requires-Dist: toml
Requires-Dist: rich>=10.0.0
Requires-Dist: shortuuid
Requires-Dist: uvicorn
Requires-Dist: tenacity>=8.2.2
Requires-Dist: pytz
Requires-Dist: cachetools
Requires-Dist: GitPython
Requires-Dist: PyYAML
Requires-Dist: typing_inspect>=0.9.0
Requires-Dist: huggingface_hub
Requires-Dist: jinja2
Requires-Dist: python-multipart
Requires-Dist: portalocker
Requires-Dist: aiofiles
Provides-Extra: dev
Requires-Dist: black==24.10.0; extra == "dev"
Requires-Dist: pylint==3.3.1; extra == "dev"
Requires-Dist: pytest==8.3.3; extra == "dev"
